ogmios/__init__.py
ogmios/loaders.py
django_ogmios-0.12.0.dist-info/LICENSE
django_ogmios-0.12.0.dist-info/METADATA
django_ogmios-0.12.0.dist-info/WHEEL
django_ogmios-0.12.0.dist-info/top_level.txt
django_ogmios-0.12.0.dist-info/RECORD
