Metadata-Version: 2.2
Name: django-ogmios
Version: 0.12.0
Summary: Just sends email. Simple, easy, multiformat.
Home-page: https://github.com/fusionbox/django-ogmios
Author: Fusionbox, Inc.
Author-email: programmers@fusionbox.com
Keywords: email send easy simple helpers django
Classifier: Development Status :: 4 - Beta
Classifier: Framework :: Django
Classifier: Intended Audience :: Developers
Classifier: License :: OSI Approved :: BSD License
Classifier: Programming Language :: Python :: 2.7
Classifier: Programming Language :: Python :: 3.4
Classifier: Programming Language :: Python :: 3.5
Classifier: Topic :: Communications :: Email
Classifier: Topic :: Software Development :: Libraries
License-File: LICENSE
Requires-Dist: Django>=1.11
Requires-Dist: PyYAML
Requires-Dist: Markdown
Requires-Dist: html2text
Requires-Dist: six
Dynamic: author
Dynamic: author-email
Dynamic: classifier
Dynamic: description
Dynamic: home-page
Dynamic: keywords
Dynamic: requires-dist
Dynamic: summary
